{
  "nodes": [
    {"id": "1","name":"1","img":"./assets/img/1.webp","val": 2},
    {"id": "2","name":"2","img":"./assets/img/2.webp","val": 2},
    {"id": "3","name":"3","img":"./assets/img/3.webp","val": 2},
    {"id": "4","name":"4","img":"./assets/img/4.webp","val": 2},
    {"id": "5","name":"5","img":"./assets/img/5.webp","val": 2},
    {"id": "6","name":"6","img":"./assets/img/6.webp","val": 2},
    {"id": "7","name":"7","img":"./assets/img/7.webp","val": 2},
    {"id": "8","name":"8","img":"./assets/img/8.webp","val": 2},
    {"id": "9","name":"9","img":"./assets/img/9.webp","val": 2},
    {"id": "10","name":"10","img":"./assets/img/10.webp","val": 2},
    {"id": "11","name":"11","img":"./assets/img/11.webp","val": 2},
    {"id": "12","name":"12","img":"./assets/img/12.webp","val": 2},
    {"id": "13","name":"13","img":"./assets/img/13.webp","val": 2},
    {"id": "14","name":"14","img":"./assets/img/14.webp","val": 2},
    {"id": "15","name":"15","img":"./assets/img/15.webp","val": 2},
    {"id": "16","name":"16","img":"./assets/img/16.webp","val": 2},
    {"id": "17","name":"17","img":"./assets/img/17.webp","val": 2},
    {"id": "18","name":"18","img":"./assets/img/18.webp","val": 2},
    {"id": "19","name":"19","img":"./assets/img/19.webp","val": 2},
    {"id": "20","name":"20","img":"./assets/img/20.webp","val": 2},
    {"id": "21","name":"21","img":"./assets/img/21.webp","val": 2},
    {"id": "22","name":"22","img":"./assets/img/22.webp","val": 2},
    {"id": "23","name":"23","img":"./assets/img/23.webp","val": 2}
  ],
  "links": []
}